CircDEAS/CircDEAS.py
CircDEAS/__init__.py
circdeas-1.0.dist-info/licenses/LICENSE
circdeas-1.0.dist-info/METADATA
circdeas-1.0.dist-info/WHEEL
circdeas-1.0.dist-info/entry_points.txt
circdeas-1.0.dist-info/top_level.txt
circdeas-1.0.dist-info/RECORD
