Metadata-Version: 2.4
Name: CircDEAS
Version: 1.0
Summary: CircDEAS differential PSI calculation tool.
Author-email: Zhao Yajing <zhao13833108617@163.com>
License: MIT
Requires-Python: >=3.6
License-File: LICENSE
Requires-Dist: numpy
Requires-Dist: pandas
Dynamic: license-file
